Workbook
Name Category: Data!$F$2:$F$301
Name Customer: Data!$C$2:$C$301
Name Discount: Data!$K$2:$K$301
Name DiscountTiers: Lookup_Tables!$G$5:$H$8
Name OrderDate: Data!$B$2:$B$301
Name OrderID: Data!$A$2:$A$301
Name PeopleTable: Lookup_Tables!$A$5:$B$8
Name ProductName: Data!$H$2:$H$301
Name Profit: Data!$L$2:$L$301
Name Quantity: Data!$J$2:$J$301
Name Region: Data!$E$2:$E$301
Name ReturnsTable: Lookup_Tables!$D$5:$E$300
Name Sales: Data!$I$2:$I$301
Name Segment: Data!$D$2:$D$301
Name SubCategory: Data!$G$2:$G$301

Sheet Data
A1: Order ID | B1: Order Date | C1: Customer Name | D1: Segment | E1: Region | F1: Category | G1: Sub-Category | H1: Product Name | I1: Sales | J1: Quantity | K1: Discount | L1: Profit
A2: CA-2026-192314 | B2: 46291 | C2: Jennifer Sheldon | D2: Corporate | E2: East | F2: Office Supplies | G2: Paper | H2: Hammermill Color Copier Paper (28Lb. and 96 Bright) | I2: 9.99 | J2: 1 | K2: 0 | L2: 4.4955
A3: US-2023-166863 | B3: 45097 | C3: Sam Craven | D3: Consumer | E3: Central | F3: Technology | G3: Phones | H3: HTC One Mini | I3: 201.584 | J3: 2 | K3: 0.2 | L3: 20.1584
A4: US-2023-147704 | B4: 45246 | C4: Steven Roelle | D4: Home Office | E4: Central | F4: Office Supplies | G4: Storage | H4: File Shuttle II and Handi-File, Black | I4: 169.45 | J4: 5 | K4: 0 | L4: 42.3625
A5: US-2023-163468 | B5: 45248 | C5: Joe Kamberova | D5: Consumer | E5: Central | F5: Office Supplies | G5: Storage | H5: Fellowes Stor/Drawer Steel Plus Storage Drawers | I5: 381.72 | J5: 5 | K5: 0.2 | L5: -66.801
A6: US-2026-102288 | B6: 46192 | C6: Zuschuss Carroll | D6: Consumer | E6: Central | F6: Office Supplies | G6: Appliances | H6: Holmes Visible Mist Ultrasonic Humidifier with 2.3-Gallon Output per Day, Replacement Filter | I6: 2.264 | J6: 1 | K6: 0.8 | L6: -5.2072
A7: US-2026-160899 | B7: 46245 | C7: Daniel Raglin | D7: Home Office | E7: South | F7: Office Supplies | G7: Binders | H7: Satellite Sectional Post Binders | I7: 477.51 | J7: 11 | K7: 0 | L7: 219.6546
A8: US-2025-138695 | B8: 45805 | C8: Kimberly Carter | D8: Corporate | E8: South | F8: Furniture | G8: Chairs | H8: Novimex Fabric Task Chair | I8: 390.272 | J8: 8 | K8: 0.2 | L8: -24.392
A9: US-2026-107132 | B9: 46199 | C9: Scott Cohen | D9: Corporate | E9: East | F9: Office Supplies | G9: Supplies | H9: Acme Preferred Stainless Steel Scissors | I9: 28.4 | J9: 5 | K9: 0 | L9: 8.236
A10: US-2024-133242 | B10: 45461 | C10: Keith Herrera | D10: Consumer | E10: South | F10: Office Supplies | G10: Binders | H10: Wilson Jones International Size A4 Ring Binders | I10: 34.6 | J10: 2 | K10: 0 | L10: 16.608
A11: US-2025-121748 | B11: 45954 | C11: Victoria Wilson | D11: Corporate | E11: West | F11: Technology | G11: Accessories | H11: Micro Innovations USB RF Wireless Keyboard with Mouse | I11: 100 | J11: 4 | K11: 0 | L11: 21
A12: US-2026-149706 | B12: 46367 | C12: Alejandro Savely | D12: Corporate | E12: Central | F12: Technology | G12: Accessories | H12: Enermax Briskie RF Wireless Keyboard and Mouse Combo | I12: 116.312 | J12: 7 | K12: 0.2 | L12: 23.2624
A13: US-2026-148922 | B13: 46366 | C13: Stephanie Ulpright | D13: Home Office | E13: South | F13: Technology | G13: Phones | H13: Cyber Acoustics AC-202b Speech Recognition Stereo Headset | I13: 38.97 | J13: 3 | K13: 0 | L13: 0.7794
... A301: US-2026-140585 | B301: 46374 | C301: Russell Applegate | D301: Consumer | E301: West | F301: Technology | G301: Accessories | H301: Logitech Illuminated - Keyboard | I301: 119.98 | J301: 2 | K301: 0 | L301: 57.5904

Sheet Lookup_Tables
A1: Lookup Tables
A4: Regional Manager | B4: Region | D4: Order ID | E4: Returned | G4: Discount from | H4: Tier
A5: Sadie Pawthorne | B5: West | D5: US-2023-100762 | E5: Yes | G5: 0 | H5: No discount
A6: Chuck Magee | B6: East | D6: US-2023-100867 | E6: Yes | G6: 0.05 | H6: Low
A7: Roxanne Rodriguez | B7: Central | D7: US-2023-102652 | E7: Yes | G7: 0.2 | H7: Medium
A8: Fred Suzuki | B8: South | D8: US-2023-103373 | E8: Yes | G8: 0.4 | H8: High
D9: US-2023-103744 | E9: Yes
D10: US-2023-103940 | E10: Yes
D11: US-2023-104829 | E11: Yes
D12: US-2023-105270 | E12: Yes
D13: US-2023-108609 | E13: Yes
D14: US-2023-108861 | E14: Yes
D15: US-2023-109918 | E15: Yes
D16: US-2023-110786 | E16: Yes
D17: US-2023-111871 | E17: Yes
D18: US-2023-116785 | E18: Yes
D19: US-2023-123225 | E19: Yes
D20: US-2023-123253 | E20: Yes
... D300: US-2026-155999 | E300: Yes

Sheet Lookup
A1: Lookup Functions: VLOOKUP, INDEX/MATCH, XLOOKUP
A4: Example | B4: Input | C4: Result
A5: 1. VLOOKUP exact: was this order returned? | B5: US-2023-103940 | C5: =IFERROR(VLOOKUP(B5,ReturnsTable,2,FALSE()),"Not returned") -> Yes
A6: Same, order that was not returned | B6: CA-2026-192314 | C6: =IFERROR(VLOOKUP(B6,ReturnsTable,2,FALSE()),"Not returned") -> Not returned
A7: 2. VLOOKUP approximate: discount tier | B7: 0.3 | C7: =VLOOKUP(B7,DiscountTiers,2,TRUE()) -> Medium
A8: 3. INDEX/MATCH: manager for a region | B8: West | C8: =INDEX(Lookup_Tables!$A$5:$A$8,MATCH(B8,Lookup_Tables!$B$5:$B$8,0)) -> Sadie Pawthorne
A9: INDEX/MATCH: sales of an order | B9: CA-2026-192314 | C9: =INDEX(Sales,MATCH(B9,OrderID,0)) -> 9.99
A16: Edge-case tests
A17: Test | B17: Input | C17: Result
A18: Blank lookup cell | C18: =IF(B18="","Enter an Order ID",IFERROR(VLOOKUP(B18,ReturnsTable,2,FALSE()),"Not returned")) -> Enter an Order ID
A19: Order ID that does not exist | B19: XX-0000-000000 | C19: =IFERROR(VLOOKUP(B19,ReturnsTable,2,FALSE()),"Not returned") -> Not returned
A20: Extra space at the end of the ID | B20: US-2023-103940 | C20: =IFERROR(VLOOKUP(B20,ReturnsTable,2,FALSE()),"Not returned") -> Not returned
A21: Same input cleaned with TRIM | B21: US-2023-103940 | C21: =IFERROR(VLOOKUP(TRIM(B21),ReturnsTable,2,FALSE()),"Not returned") -> Yes

Sheet IF_Functions
A1: IF, Nested IF, AND, OR, IFERROR
A3: Order ID | B3: Sales | C3: Discount | D3: Profit | E3: Profit Status IF (nested) | F3: Profit Margin IF + divide | G3: Margin Grade nested IF | H3: Risky Discount? IF + AND
A4: =Data!A2 -> CA-2026-192314 | B4: =Data!I2 -> 9.99 | C4: =Data!K2 -> 0 | D4: =Data!L2 -> 4.4955 | E4: =IF(D4>0,"Profit",IF(D4<0,"Loss","Break-even")) -> Profit | F4: =IF(B4=0,0,D4/B4) -> 0.45 | G4: =IF(F4>=0.2,"High",IF(F4>=0.1,"Medium",IF(F4>=0,"Low","Loss"))) -> High | H4: =IF(AND(C4>0.3,D4<0),"Risky","OK") -> OK
A5: =Data!A3 -> US-2023-166863 | B5: =Data!I3 -> 201.584 | C5: =Data!K3 -> 0.2 | D5: =Data!L3 -> 20.1584 | E5: =IF(D5>0,"Profit",IF(D5<0,"Loss","Break-even")) -> Profit | F5: =IF(B5=0,0,D5/B5) -> 0.1 | G5: =IF(F5>=0.2,"High",IF(F5>=0.1,"Medium",IF(F5>=0,"Low","Loss"))) -> Medium | H5: =IF(AND(C5>0.3,D5<0),"Risky","OK") -> OK
A6: =Data!A4 -> US-2023-147704 | B6: =Data!I4 -> 169.45 | C6: =Data!K4 -> 0 | D6: =Data!L4 -> 42.3625 | E6: =IF(D6>0,"Profit",IF(D6<0,"Loss","Break-even")) -> Profit | F6: =IF(B6=0,0,D6/B6) -> 0.25 | G6: =IF(F6>=0.2,"High",IF(F6>=0.1,"Medium",IF(F6>=0,"Low","Loss"))) -> High | H6: =IF(AND(C6>0.3,D6<0),"Risky","OK") -> OK
A7: =Data!A5 -> US-2023-163468 | B7: =Data!I5 -> 381.72 | C7: =Data!K5 -> 0.2 | D7: =Data!L5 -> -66.801 | E7: =IF(D7>0,"Profit",IF(D7<0,"Loss","Break-even")) -> Loss | F7: =IF(B7=0,0,D7/B7) -> -0.175 | G7: =IF(F7>=0.2,"High",IF(F7>=0.1,"Medium",IF(F7>=0,"Low","Loss"))) -> Loss | H7: =IF(AND(C7>0.3,D7<0),"Risky","OK") -> OK
A8: =Data!A6 -> US-2026-102288 | B8: =Data!I6 -> 2.264 | C8: =Data!K6 -> 0.8 | D8: =Data!L6 -> -5.2072 | E8: =IF(D8>0,"Profit",IF(D8<0,"Loss","Break-even")) -> Loss | F8: =IF(B8=0,0,D8/B8) -> -2.3 | G8: =IF(F8>=0.2,"High",IF(F8>=0.1,"Medium",IF(F8>=0,"Low","Loss"))) -> Loss | H8: =IF(AND(C8>0.3,D8<0),"Risky","OK") -> Risky
A9: =Data!A7 -> US-2026-160899 | B9: =Data!I7 -> 477.51 | C9: =Data!K7 -> 0 | D9: =Data!L7 -> 219.6546 | E9: =IF(D9>0,"Profit",IF(D9<0,"Loss","Break-even")) -> Profit | F9: =IF(B9=0,0,D9/B9) -> 0.46 | G9: =IF(F9>=0.2,"High",IF(F9>=0.1,"Medium",IF(F9>=0,"Low","Loss"))) -> High | H9: =IF(AND(C9>0.3,D9<0),"Risky","OK") -> OK
A10: =Data!A8 -> US-2025-138695 | B10: =Data!I8 -> 390.272 | C10: =Data!K8 -> 0.2 | D10: =Data!L8 -> -24.392 | E10: =IF(D10>0,"Profit",IF(D10<0,"Loss","Break-even")) -> Loss | F10: =IF(B10=0,0,D10/B10) -> -0.0625 | G10: =IF(F10>=0.2,"High",IF(F10>=0.1,"Medium",IF(F10>=0,"Low","Loss"))) -> Loss | H10: =IF(AND(C10>0.3,D10<0),"Risky","OK") -> OK
A11: =Data!A9 -> US-2026-107132 | B11: =Data!I9 -> 28.4 | C11: =Data!K9 -> 0 | D11: =Data!L9 -> 8.236 | E11: =IF(D11>0,"Profit",IF(D11<0,"Loss","Break-even")) -> Profit | F11: =IF(B11=0,0,D11/B11) -> 0.29 | G11: =IF(F11>=0.2,"High",IF(F11>=0.1,"Medium",IF(F11>=0,"Low","Loss"))) -> High | H11: =IF(AND(C11>0.3,D11<0),"Risky","OK") -> OK
A12: =Data!A10 -> US-2024-133242 | B12: =Data!I10 -> 34.6 | C12: =Data!K10 -> 0 | D12: =Data!L10 -> 16.608 | E12: =IF(D12>0,"Profit",IF(D12<0,"Loss","Break-even")) -> Profit | F12: =IF(B12=0,0,D12/B12) -> 0.48 | G12: =IF(F12>=0.2,"High",IF(F12>=0.1,"Medium",IF(F12>=0,"Low","Loss"))) -> High | H12: =IF(AND(C12>0.3,D12<0),"Risky","OK") -> OK
A13: =Data!A11 -> US-2025-121748 | B13: =Data!I11 -> 100 | C13: =Data!K11 -> 0 | D13: =Data!L11 -> 21 | E13: =IF(D13>0,"Profit",IF(D13<0,"Loss","Break-even")) -> Profit | F13: =IF(B13=0,0,D13/B13) -> 0.21 | G13: =IF(F13>=0.2,"High",IF(F13>=0.1,"Medium",IF(F13>=0,"Low","Loss"))) -> High | H13: =IF(AND(C13>0.3,D13<0),"Risky","OK") -> OK
A14: =Data!A12 -> US-2026-149706 | B14: =Data!I12 -> 116.312 | C14: =Data!K12 -> 0.2 | D14: =Data!L12 -> 23.2624 | E14: =IF(D14>0,"Profit",IF(D14<0,"Loss","Break-even")) -> Profit | F14: =IF(B14=0,0,D14/B14) -> 0.2 | G14: =IF(F14>=0.2,"High",IF(F14>=0.1,"Medium",IF(F14>=0,"Low","Loss"))) -> High | H14: =IF(AND(C14>0.3,D14<0),"Risky","OK") -> OK
A15: =Data!A13 -> US-2026-148922 | B15: =Data!I13 -> 38.97 | C15: =Data!K13 -> 0 | D15: =Data!L13 -> 0.7794 | E15: =IF(D15>0,"Profit",IF(D15<0,"Loss","Break-even")) -> Profit | F15: =IF(B15=0,0,D15/B15) -> 0.02 | G15: =IF(F15>=0.2,"High",IF(F15>=0.1,"Medium",IF(F15>=0,"Low","Loss"))) -> Low | H15: =IF(AND(C15>0.3,D15<0),"Risky","OK") -> OK
... A23: =Data!A21 -> US-2025-159639 | B23: =Data!I21 -> 31.56 | C23: =Data!K21 -> 0 | D23: =Data!L21 -> 10.4148 | E23: =IF(D23>0,"Profit",IF(D23<0,"Loss","Break-even")) -> Profit | F23: =IF(B23=0,0,D23/B23) -> 0.33 | G23: =IF(F23>=0.2,"High",IF(F23>=0.1,"Medium",IF(F23>=0,"Low","Loss"))) -> High | H23: =IF(AND(C23>0.3,D23<0),"Risky","OK") -> OK
A26: Edge-case tests (blank cell and text vs number)
A27: Test | B27: Input | C27: Result
A28: Blank cell | C28: =IF(B28="","Blank",IF(B28>0,"Profit","Loss")) -> Blank
A29: Number stored as text | B29: 150 | C29: =IF(ISNUMBER(B29),"Number","Text: use VALUE()") -> Text: use VALUE()
A30: Same text converted | B30: 150 | C30: =VALUE(B30)+10 -> 160

Sheet SUMIFS_COUNTIFS
A1: SUMIF vs SUMIFS, COUNTIF(S), AVERAGEIFS
A3: Region input | B3: West
A4: Category input | B4: Furniture
A5: Sales greater than | B5: 500
A7: Question | B7: Result | F7: Note
A8: Sales in the region (SUMIF) | B8: =SUMIF(Region,B3,Sales) -> 13195.692 | C8: SUMIF(Region, B3, Sales) | F8: One condition
A9: Sales in the region (SUMIFS) | B9: =SUMIFS(Sales,Region,B3) -> 13195.692 | C9: SUMIFS(Sales, Region, B3) | F9: Same answer; SUMIFS puts the sum range FIRST
A10: Sales in region AND category (SUMIFS) | B10: =SUMIFS(Sales,Region,B3,Category,B4) -> 3059.458 | C10: SUMIFS(Sales, Region, B3, Category, B4) | F10: Two conditions: only SUMIFS can do this
A11: Sales above a value (operator in criteria) | B11: =SUMIFS(Sales,Sales,">"&B5) -> 26727.635 | C11: SUMIFS(Sales, Sales, ">"&B5 | F11: Join the operator with &
A12: Number of rows in the region (COUNTIF) | B12: =COUNTIF(Region,B3) -> 99 | C12: COUNTIF(Region, B3) | F12: Counts rows
A13: Rows in region AND category (COUNTIFS) | B13: =COUNTIFS(Region,B3,Category,B4) -> 10 | C13: COUNTIFS(Region, B3, Category, B4) | F13: Two conditions
A14: Loss-making rows in the region (COUNTIFS) | B14: =COUNTIFS(Region,B3,Profit,"<0") -> 6 | C14: COUNTIFS(Region, B3, Profit, "<0") | F14: Criteria with an operator
A15: Average discount, region and category (AVERAGEIFS) | B15: =AVERAGEIFS(Discount,Region,B3,Category,B4) -> 0.17 | C15: AVERAGEIFS(Discount, Region, B3, Category, B4) | F15: Average range comes first
A16: Check: SUMIF equals SUMIFS? | B16: =IF(ROUND(B8-B9,2)=0,"Yes","No") -> Yes | C16: IF(ROUND(B8-B9,2)=0,"Yes","No") | F16: Both formulas should agree for one condition
A19: Sales matrix: Region x Category (one SUMIFS copied across with mixed references)
A20: Region | B20: Furniture | C20: Office Supplies | D20: Technology | E20: Total
A21: Central | B21: =SUMIFS(Sales,Region,$A21,Category,B$20) -> 2245.949 | C21: =SUMIFS(Sales,Region,$A21,Category,C$20) -> 2740.047 | D21: =SUMIFS(Sales,Region,$A21,Category,D$20) -> 4570.698 | E21: =SUM(B21:D21) -> 9556.694
A22: East | B22: =SUMIFS(Sales,Region,$A22,Category,B$20) -> 4717.856 | C22: =SUMIFS(Sales,Region,$A22,Category,C$20) -> 2407.964 | D22: =SUMIFS(Sales,Region,$A22,Category,D$20) -> 6593.032 | E22: =SUM(B22:D22) -> 13718.852
A23: South | B23: =SUMIFS(Sales,Region,$A23,Category,B$20) -> 3062.722 | C23: =SUMIFS(Sales,Region,$A23,Category,C$20) -> 2444.132 | D23: =SUMIFS(Sales,Region,$A23,Category,D$20) -> 11873.352 | E23: =SUM(B23:D23) -> 17380.206
A24: West | B24: =SUMIFS(Sales,Region,$A24,Category,B$20) -> 3059.458 | C24: =SUMIFS(Sales,Region,$A24,Category,C$20) -> 6961.428 | D24: =SUMIFS(Sales,Region,$A24,Category,D$20) -> 3174.806 | E24: =SUM(B24:D24) -> 13195.692
A25: Total | B25: =SUM(B21:B24) -> 13085.985 | C25: =SUM(C21:C24) -> 14553.571 | D25: =SUM(D21:D24) -> 26211.888 | E25: =SUM(E21:E24) -> 53851.444
A26: Check against SUM(Sales) | B26: =ROUND(E25-SUM(Sales),2) -> 0 | C26: 0 means the matrix matches the data

Sheet Text_Functions
A1: Text Functions
A3: Order ID | B3: Customer Name | C3: LEFT country code | D3: MID year | E3: RIGHT last 6 chars | F3: LEN length | G3: FIND position of space | H3: First Name LEFT+FIND | I3: Last Name MID+FIND | J3: UPPER | K3: Name - Order & join | L3: Order Date TEXT
A4: =Data!A2 -> CA-2026-192314 | B4: =Data!C2 -> Jennifer Sheldon | C4: =LEFT(A4,2) -> CA | D4: =MID(A4,4,4) -> 2026 | E4: =RIGHT(A4,6) -> 192314 | F4: =LEN(B4) -> 16 | G4: =FIND(" ",B4) -> 9 | H4: =LEFT(B4,G4-1) -> Jennifer | I4: =MID(B4,G4+1,LEN(B4)) -> Sheldon | J4: =UPPER(B4) -> JENNIFER SHELDON | K4: =B4&" - "&A4 -> Jennifer Sheldon - CA-2026-192314 | L4: =TEXT(Data!B2,"dd-mmm-yyyy") -> 26-Sep-2026
A5: =Data!A3 -> US-2023-166863 | B5: =Data!C3 -> Sam Craven | C5: =LEFT(A5,2) -> US | D5: =MID(A5,4,4) -> 2023 | E5: =RIGHT(A5,6) -> 166863 | F5: =LEN(B5) -> 10 | G5: =FIND(" ",B5) -> 4 | H5: =LEFT(B5,G5-1) -> Sam | I5: =MID(B5,G5+1,LEN(B5)) -> Craven | J5: =UPPER(B5) -> SAM CRAVEN | K5: =B5&" - "&A5 -> Sam Craven - US-2023-166863 | L5: =TEXT(Data!B3,"dd-mmm-yyyy") -> 20-Jun-2023
A6: =Data!A4 -> US-2023-147704 | B6: =Data!C4 -> Steven Roelle | C6: =LEFT(A6,2) -> US | D6: =MID(A6,4,4) -> 2023 | E6: =RIGHT(A6,6) -> 147704 | F6: =LEN(B6) -> 13 | G6: =FIND(" ",B6) -> 7 | H6: =LEFT(B6,G6-1) -> Steven | I6: =MID(B6,G6+1,LEN(B6)) -> Roelle | J6: =UPPER(B6) -> STEVEN ROELLE | K6: =B6&" - "&A6 -> Steven Roelle - US-2023-147704 | L6: =TEXT(Data!B4,"dd-mmm-yyyy") -> 16-Nov-2023
A7: =Data!A5 -> US-2023-163468 | B7: =Data!C5 -> Joe Kamberova | C7: =LEFT(A7,2) -> US | D7: =MID(A7,4,4) -> 2023 | E7: =RIGHT(A7,6) -> 163468 | F7: =LEN(B7) -> 13 | G7: =FIND(" ",B7) -> 4 | H7: =LEFT(B7,G7-1) -> Joe | I7: =MID(B7,G7+1,LEN(B7)) -> Kamberova | J7: =UPPER(B7) -> JOE KAMBEROVA | K7: =B7&" - "&A7 -> Joe Kamberova - US-2023-163468 | L7: =TEXT(Data!B5,"dd-mmm-yyyy") -> 18-Nov-2023
A8: =Data!A6 -> US-2026-102288 | B8: =Data!C6 -> Zuschuss Carroll | C8: =LEFT(A8,2) -> US | D8: =MID(A8,4,4) -> 2026 | E8: =RIGHT(A8,6) -> 102288 | F8: =LEN(B8) -> 16 | G8: =FIND(" ",B8) -> 9 | H8: =LEFT(B8,G8-1) -> Zuschuss | I8: =MID(B8,G8+1,LEN(B8)) -> Carroll | J8: =UPPER(B8) -> ZUSCHUSS CARROLL | K8: =B8&" - "&A8 -> Zuschuss Carroll - US-2026-102288 | L8: =TEXT(Data!B6,"dd-mmm-yyyy") -> 19-Jun-2026
A9: =Data!A7 -> US-2026-160899 | B9: =Data!C7 -> Daniel Raglin | C9: =LEFT(A9,2) -> US | D9: =MID(A9,4,4) -> 2026 | E9: =RIGHT(A9,6) -> 160899 | F9: =LEN(B9) -> 13 | G9: =FIND(" ",B9) -> 7 | H9: =LEFT(B9,G9-1) -> Daniel | I9: =MID(B9,G9+1,LEN(B9)) -> Raglin | J9: =UPPER(B9) -> DANIEL RAGLIN | K9: =B9&" - "&A9 -> Daniel Raglin - US-2026-160899 | L9: =TEXT(Data!B7,"dd-mmm-yyyy") -> 11-Aug-2026
A10: =Data!A8 -> US-2025-138695 | B10: =Data!C8 -> Kimberly Carter | C10: =LEFT(A10,2) -> US | D10: =MID(A10,4,4) -> 2025 | E10: =RIGHT(A10,6) -> 138695 | F10: =LEN(B10) -> 15 | G10: =FIND(" ",B10) -> 9 | H10: =LEFT(B10,G10-1) -> Kimberly | I10: =MID(B10,G10+1,LEN(B10)) -> Carter | J10: =UPPER(B10) -> KIMBERLY CARTER | K10: =B10&" - "&A10 -> Kimberly Carter - US-2025-138695 | L10: =TEXT(Data!B8,"dd-mmm-yyyy") -> 28-May-2025
A11: =Data!A9 -> US-2026-107132 | B11: =Data!C9 -> Scott Cohen | C11: =LEFT(A11,2) -> US | D11: =MID(A11,4,4) -> 2026 | E11: =RIGHT(A11,6) -> 107132 | F11: =LEN(B11) -> 11 | G11: =FIND(" ",B11) -> 6 | H11: =LEFT(B11,G11-1) -> Scott | I11: =MID(B11,G11+1,LEN(B11)) -> Cohen | J11: =UPPER(B11) -> SCOTT COHEN | K11: =B11&" - "&A11 -> Scott Cohen - US-2026-107132 | L11: =TEXT(Data!B9,"dd-mmm-yyyy") -> 26-Jun-2026
A12: =Data!A10 -> US-2024-133242 | B12: =Data!C10 -> Keith Herrera | C12: =LEFT(A12,2) -> US | D12: =MID(A12,4,4) -> 2024 | E12: =RIGHT(A12,6) -> 133242 | F12: =LEN(B12) -> 13 | G12: =FIND(" ",B12) -> 6 | H12: =LEFT(B12,G12-1) -> Keith | I12: =MID(B12,G12+1,LEN(B12)) -> Herrera | J12: =UPPER(B12) -> KEITH HERRERA | K12: =B12&" - "&A12 -> Keith Herrera - US-2024-133242 | L12: =TEXT(Data!B10,"dd-mmm-yyyy") -> 18-Jun-2024
A13: =Data!A11 -> US-2025-121748 | B13: =Data!C11 -> Victoria Wilson | C13: =LEFT(A13,2) -> US | D13: =MID(A13,4,4) -> 2025 | E13: =RIGHT(A13,6) -> 121748 | F13: =LEN(B13) -> 15 | G13: =FIND(" ",B13) -> 9 | H13: =LEFT(B13,G13-1) -> Victoria | I13: =MID(B13,G13+1,LEN(B13)) -> Wilson | J13: =UPPER(B13) -> VICTORIA WILSON | K13: =B13&" - "&A13 -> Victoria Wilson - US-2025-121748 | L13: =TEXT(Data!B11,"dd-mmm-yyyy") -> 24-Oct-2025
A16: Cleaning messy text: TRIM, PROPER, LOWER, SUBSTITUTE, CONCATENATE
A17: Messy input | B17: TRIM | C17: PROPER(TRIM) | D17: LOWER | E17: SUBSTITUTE replace - with / | F17: CONCATENATE
A18: aLiCe smith | B18: =TRIM(A18) -> aLiCe smith | C18: =PROPER(TRIM(A18)) -> Alice Smith | D18: =LOWER(A18) -> alice smith | E18: =SUBSTITUTE(A18,"-","/") -> aLiCe smith | F18: =CONCATENATE("Customer: ",TRIM(A18)) -> Customer: aLiCe smith
A19: US-2023-103800 | B19: =TRIM(A19) -> US-2023-103800 | C19: =PROPER(TRIM(A19)) -> Us-2023-103800 | D19: =LOWER(A19) -> us-2023-103800 | E19: =SUBSTITUTE(A19,"-","/") -> US/2023/103800 | F19: =CONCATENATE("Customer: ",TRIM(A19)) -> Customer: US-2023-103800

Sheet Notes
A1: Excel Formulas & Functions: Notes
A4: Function | B4: When to use it
A5: VLOOKUP | B5: Simple exact lookups, like order to returned status
A6: INDEX/MATCH | B6: Find an answer that is to the left of the lookup column
A7: XLOOKUP | B7: Excel 365/2021 or Google Sheets
A8: IF / nested IF | B8: Label a row like Profit or Loss, grades, flags
A9: AND / OR | B9: Flag rows that meet all (AND) or any (OR) conditions
A10: SUMIF vs SUMIFS | B10: SUMIF: one condition. SUMIFS: one or more conditions
A11: COUNTIFS | B11: Count rows that meet conditions
A12: AVERAGEIFS | B12: Average discount per region
A13: TRIM / PROPER / UPPER / LOWER | B13: Cleaning imported text before lookups
